watch_bot/__init__.py
watch_bot/_bot.py
watch_bot/_dialog.py
watch_bot/_response.py
watch_bot/prompt.j2
watch_bot-0.2.3.dist-info/LICENSE
watch_bot-0.2.3.dist-info/METADATA
watch_bot-0.2.3.dist-info/WHEEL
watch_bot-0.2.3.dist-info/top_level.txt
watch_bot-0.2.3.dist-info/RECORD
