Metadata-Version: 2.1
Name: watch-bot
Version: 0.2.3
Summary: Implementation of the watchbot, to control the behaviour of a LLM-based chatbot
Author-email: Francesco Calcavecchia <francesco086@gmail.com>
Maintainer-email: Francesco Calcavecchia <francesco086@gmail.com>
License: MIT
Classifier: Programming Language :: Python
Requires-Python: >=3.9
License-File: LICENSE
Requires-Dist: pydantic (~=1.0)
Requires-Dist: jinja2 (~=3.0)
Requires-Dist: openai (~=0.27)
